syndalib/__init__.py
syndalib/drawer.py
syndalib/modelgen.py
syndalib/plot.py
syndalib/syn2d.py
syndalib/makers/__init__.py
syndalib/makers/circle_maker.py
syndalib/makers/conic_maker.py
syndalib/makers/ellipse_maker.py
syndalib/makers/line_maker.py
syndalib/makers/maker.py
syndalib/utils/__init__.py
syndalib/utils/config.py
syndalib/utils/utils.py
syndalib-0.1.1.dist-info/METADATA
syndalib-0.1.1.dist-info/WHEEL
syndalib-0.1.1.dist-info/top_level.txt
syndalib-0.1.1.dist-info/RECORD
