Metadata-Version: 2.1
Name: syndalib
Version: 0.1.1
Summary: synthetic point cloud library
Home-page: UNKNOWN
Author: William Bonvini
Author-email: UNKNOWN
License: MIT
Platform: UNKNOWN
Requires-Dist: pytest-runner
